ceointerviews/__init__.py
ceointerviews/client.py
ceointerviews-0.1.3.dist-info/METADATA
ceointerviews-0.1.3.dist-info/WHEEL
ceointerviews-0.1.3.dist-info/top_level.txt
ceointerviews-0.1.3.dist-info/RECORD
