Metadata-Version: 2.4
Name: ceointerviews
Version: 0.1.3
Summary: Python client for the CEOInterviews API at https://ceointerviews.ai/api_docs/
Home-page: https://github.com/codelucas/ceointerviews
Author: Lucas Ou-Yang
Author-email: lucas@ceointerviews.ai
Project-URL: Bug Tracker, https://github.com/codelucas/ceointerviews/issues
Classifier: Programming Language :: Python :: 3
Classifier: License :: OSI Approved :: MIT License
Classifier: Operating System :: OS Independent
Classifier: Development Status :: 4 - Beta
Classifier: Intended Audience :: Developers
Classifier: Topic :: Software Development :: Libraries
Requires-Python: >=3.6
Requires-Dist: requests>=2.25.0
Requires-Dist: urllib3>=1.26.0
Requires-Dist: typing-extensions>=4.0.0
Requires-Dist: json5>=0.9.6
